CHANGES.txt
buildout.cfg
setup.py
src/classix/README.txt
src/classix/__init__.py
src/classix/components.py
src/classix/directive.py
src/classix/meta.py
src/classix/tests.py
src/classix.egg-info/PKG-INFO
src/classix.egg-info/SOURCES.txt
src/classix.egg-info/dependency_links.txt
src/classix.egg-info/not-zip-safe
src/classix.egg-info/requires.txt
src/classix.egg-info/top_level.txt