Metadata-Version: 1.0
Name: classix
Version: 0.5
Summary: Declarative way to associate classes with lxml XML elements.
